ssb_konjunk/__init__.py
ssb_konjunk/__main__.py
ssb_konjunk/_functions.py
ssb_konjunk/data_formating.py
ssb_konjunk/fame.py
ssb_konjunk/prompts.py
ssb_konjunk/py.typed
ssb_konjunk/rounding.py
ssb_konjunk/saving.py
ssb_konjunk/statbank_format.py
ssb_konjunk/timestamp.py
ssb_konjunk/xml_handling.py
ssb_konjunk-2.0.0.dist-info/LICENSE
ssb_konjunk-2.0.0.dist-info/METADATA
ssb_konjunk-2.0.0.dist-info/WHEEL
ssb_konjunk-2.0.0.dist-info/entry_points.txt
ssb_konjunk-2.0.0.dist-info/RECORD
