Metadata-Version: 2.3
Name: ssb-konjunk
Version: 2.0.0
Summary: SSB Konjunk 422
License: MIT
Author: Johanne Saxegaard
Author-email: jox@ssb.no
Requires-Python: >=3.10,<4.0
Classifier: Development Status :: 1 - Planning
Classifier: License :: OSI Approved :: MIT License
Classifier: Programming Language :: Python :: 3
Classifier: Programming Language :: Python :: 3.10
Classifier: Programming Language :: Python :: 3.11
Classifier: Programming Language :: Python :: 3.12
Classifier: Programming Language :: Python :: 3.13
Requires-Dist: click (>=8.0.1)
Requires-Dist: pandas (>=2.2.0)
Requires-Dist: pandas-stubs (>=2.2.2.240807)
Requires-Dist: pendulum (>=3.0.0)
Project-URL: Changelog, https://github.com/statisticsnorway/ssb-konjunk/releases
Project-URL: Documentation, https://statisticsnorway.github.io/ssb-konjunk
Project-URL: Homepage, https://github.com/statisticsnorway/ssb-konjunk
Project-URL: Repository, https://github.com/statisticsnorway/ssb-konjunk
